telemeter/__init__.py
telemeter/telemeter.py
telemeter-3.0.9.dist-info/LICENSE
telemeter-3.0.9.dist-info/METADATA
telemeter-3.0.9.dist-info/WHEEL
telemeter-3.0.9.dist-info/top_level.txt
telemeter-3.0.9.dist-info/RECORD
