Metadata-Version: 2.1
Name: telemeter
Version: 3.0.9
Summary: Retrieves information about Telenet internet usage
Home-page: https://github.com/KillianMeersman/telemeter
Author: Killian Meersman
Author-email: hi@killianm.dev
License: UNKNOWN
Keywords: telenet telemeter
Platform: UNKNOWN
Classifier: Programming Language :: Python :: 3
Classifier: License :: OSI Approved :: MIT License
Classifier: Operating System :: OS Independent
License-File: LICENSE
Requires-Dist: requests
